inversiontestproblems/__init__.py
inversiontestproblems/_version.py
inversiontestproblems/gravityforward/__init__.py
inversiontestproblems/gravityforward/auxfile.py
inversiontestproblems/gravityforward/Jupyter/Testfile.npz
inversiontestproblems/gravityforward/Jupyter/gravmodel1.txt
inversiontestproblems/gravityforward/Jupyter/testfile.npy
inversiontestproblems/gravityforward/data/Testfile.npz
inversiontestproblems/gravityforward/data/__init__.py
inversiontestproblems/gravityforward/data/gravmodel1.txt
inversiontestproblems/gravityforward/data/testfile.npy
inversion_test_test-0.0.33.dist-info/METADATA
inversion_test_test-0.0.33.dist-info/WHEEL
inversion_test_test-0.0.33.dist-info/top_level.txt
inversion_test_test-0.0.33.dist-info/RECORD
