Metadata-Version: 2.1
Name: inversion-test-test
Version: 0.0.33
Summary: A suite of forward codes for inversion testing.
Author: InLab
Classifier: Programming Language :: Python :: 3
Classifier: License :: OSI Approved :: MIT License
Classifier: Operating System :: OS Independent
Requires-Dist: requests
Requires-Dist: importlib-metadata ; python_version < "3.8"
Requires-Dist: importlib-metadata ; python_version == "3.8"
